setup.py
tailer/__init__.py
tailer.egg-info/PKG-INFO
tailer.egg-info/SOURCES.txt
tailer.egg-info/dependency_links.txt
tailer.egg-info/entry_points.txt
tailer.egg-info/top_level.txt
