Metadata-Version: 1.0
Name: tailer
Version: 0.2
Summary: Python tail is a simple implementation of GNU tail and head.
Home-page: http://code.google.com/p/pytailer/
Author: Michael Thornton
Author-email: msthornton@gmail.com
License: GPL
Keywords: tail head
Platform: UNKNOWN
Classifier: Environment :: Console
Classifier: License :: OSI Approved :: GNU General Public License (GPL)
Classifier: Programming Language :: Python
Classifier: Topic :: System :: Logging
Classifier: Topic :: Text Processing
